si4attention/__init__.py
si4attention/abstract.py
si4attention/batch_adaptive.py
si4attention/function.py
si4attention/grid.py
si4attention/hypothesis.py
si4attention/inference.py
si4attention-1.0.0.dist-info/METADATA
si4attention-1.0.0.dist-info/WHEEL
si4attention-1.0.0.dist-info/licenses/LICENSE.md
si4attention-1.0.0.dist-info/RECORD
