Metadata-Version: 2.4
Name: si4attention
Version: 1.0.0
Summary: Package for statistical test for attention in Transformers
Project-URL: repository, https://github.com/shirara1016/si4attention
Author: Takeuchi Lab
Maintainer-email: Tomohiro Shiraishi <shirara1016@gmail.com>
License-Expression: MIT
License-File: LICENSE.md
Classifier: License :: OSI Approved :: MIT License
Classifier: Programming Language :: Python :: 3.10
Classifier: Programming Language :: Python :: 3.11
Classifier: Programming Language :: Python :: 3.12
Classifier: Programming Language :: Python :: 3.13
Requires-Python: >=3.10
Requires-Dist: sicore>=2.2.0
Requires-Dist: torch>=2.5.0
Requires-Dist: tqdm>=4.66.5
